fluidly_pipenv-0.1.1-py3.7-nspkg.pth
fluidly/pipenv/__init__.py
fluidly/pipenv/generate_requirements.py
fluidly/pipenv/py.typed
fluidly_pipenv-0.1.1.dist-info/METADATA
fluidly_pipenv-0.1.1.dist-info/WHEEL
fluidly_pipenv-0.1.1.dist-info/namespace_packages.txt
fluidly_pipenv-0.1.1.dist-info/top_level.txt
fluidly_pipenv-0.1.1.dist-info/RECORD
