Metadata-Version: 2.1
Name: fluidly-pipenv
Version: 0.1.1
Summary: Pipenv helpers.
Home-page: https://github.com/fluidly/python-shared
Author: Fluidly
Author-email: tech@fluidly.com
License: UNKNOWN
Platform: UNKNOWN
Requires-Python: >=3.6.0
